odoo/addons/survey_conditional_question/README.rst
odoo/addons/survey_conditional_question/__init__.py
odoo/addons/survey_conditional_question/__manifest__.py
odoo/addons/survey_conditional_question/controllers/__init__.py
odoo/addons/survey_conditional_question/controllers/main.py
odoo/addons/survey_conditional_question/i18n/en_US.po
odoo/addons/survey_conditional_question/i18n/es.po
odoo/addons/survey_conditional_question/i18n/it.po
odoo/addons/survey_conditional_question/i18n/survey_conditional_question.pot
odoo/addons/survey_conditional_question/models/__init__.py
odoo/addons/survey_conditional_question/models/survey_question.py
odoo/addons/survey_conditional_question/models/survey_survey.py
odoo/addons/survey_conditional_question/models/survey_user_input.py
odoo/addons/survey_conditional_question/models/survey_user_input_line.py
odoo/addons/survey_conditional_question/static/description/icon.png
odoo/addons/survey_conditional_question/static/src/js/survey_conditional_questions.js
odoo/addons/survey_conditional_question/static/src/scss/survey_conditional_questions.scss
odoo/addons/survey_conditional_question/tests/__init__.py
odoo/addons/survey_conditional_question/tests/test_survey_conditional_questions.py
odoo/addons/survey_conditional_question/views/survey_question_qweb.xml
odoo/addons/survey_conditional_question/views/survey_question_views.xml
odoo14_addon_survey_conditional_question-14.0.1.0.1.dev8.dist-info/METADATA
odoo14_addon_survey_conditional_question-14.0.1.0.1.dev8.dist-info/WHEEL
odoo14_addon_survey_conditional_question-14.0.1.0.1.dev8.dist-info/top_level.txt
odoo14_addon_survey_conditional_question-14.0.1.0.1.dev8.dist-info/RECORD
